utf8_locale/__init__.py
utf8_locale/__main__.py
utf8_locale/detect.py
utf8_locale/py.typed
utf8_locale-1.0.3.dist-info/METADATA
utf8_locale-1.0.3.dist-info/WHEEL
utf8_locale-1.0.3.dist-info/entry_points.txt
utf8_locale-1.0.3.dist-info/RECORD
