Metadata-Version: 2.1
Name: utf8-locale
Version: 1.0.3
Summary: Detect a UTF-8-capable locale for running programs in
Project-URL: Homepage, https://devel.ringlet.net/devel/utf8-locale/
Project-URL: Issue Tracker, https://gitlab.com/ppentchev/utf8-locale/-/issues
Project-URL: Source Code, https://gitlab.com/ppentchev/utf8-locale
Author-email: Peter Pentchev <roam@ringlet.net>
License: BSD-2-Clause
Classifier: Development Status :: 5 - Production/Stable
Classifier: Intended Audience :: Developers
Classifier: License :: DFSG approved
Classifier: License :: Freely Distributable
Classifier: License :: OSI Approved :: BSD License
Classifier: Operating System :: OS Independent
Classifier: Programming Language :: Python
Classifier: Programming Language :: Python :: 3
Classifier: Programming Language :: Python :: 3.8
Classifier: Programming Language :: Python :: 3.9
Classifier: Programming Language :: Python :: 3.10
Classifier: Programming Language :: Python :: 3.11
Classifier: Programming Language :: Python :: 3.12
Classifier: Programming Language :: Python :: 3.13
Classifier: Topic :: Software Development :: Libraries
Classifier: Topic :: Software Development :: Libraries :: Python Modules
Requires-Python: >=3.8
